sodasql/dialects/spark_dialect.py
soda_sql_spark-2.2.2.dist-info/METADATA
soda_sql_spark-2.2.2.dist-info/WHEEL
soda_sql_spark-2.2.2.dist-info/top_level.txt
soda_sql_spark-2.2.2.dist-info/RECORD
