Metadata-Version: 2.1
Name: soda-sql-spark
Version: 2.2.2
Classifier: Development Status :: 5 - Production/Stable
Classifier: License :: OSI Approved :: Apache Software License
Classifier: Operating System :: Microsoft :: Windows
Classifier: Operating System :: MacOS :: MacOS X
Classifier: Operating System :: POSIX :: Linux
Classifier: Programming Language :: Python :: 3.7
Classifier: Programming Language :: Python :: 3.8
Classifier: Programming Language :: Python :: 3.9
Requires-Dist: soda-sql-core (==2.2.2)
Requires-Dist: pyodbc (<5.0,>=4.0)
Requires-Dist: PyHive (<1.0,>=0.6.3)
Requires-Dist: thrift (<1.0,>=0.13.0)
Requires-Dist: sasl (<1.0,>=0.3.1)
Requires-Dist: thrift-sasl (<1.0,>=0.4.3)
